cursives/__init__.py
cursives/_cache.py
cursives/text/__init__.py
cursives/text/formatting/__init__.py
cursives/text/formatting/markdown.py
cursives-0.0.1.dist-info/METADATA
cursives-0.0.1.dist-info/WHEEL
cursives-0.0.1.dist-info/entry_points.txt
cursives-0.0.1.dist-info/licenses/LICENSE
cursives-0.0.1.dist-info/RECORD
