Metadata-Version: 2.4
Name: cursives
Version: 0.0.1
Summary: Very, VERY opinionated resources to make things pretty in Python. Made for neat folks.
Author-email: Hammad Saeed <hvmmad@gmail.com>
License: MIT License
License-File: LICENSE
Requires-Python: >=3.10
Requires-Dist: docstring-parser>=0.16
Requires-Dist: pydantic>=2.11.5
Requires-Dist: rich>=14.0.0
Requires-Dist: typer>=0.16.0
Requires-Dist: typing-inspect>=0.9.0
